sqlparser/SqlParser.py
sqlparser/__init__.py
sqlparser/tests/TestSqlParser.py
sqlparser/tests/__init__.py
sqlparser/tests/mock_jaydebeapi.py
sqlparser-0.0.8.dist-info/COPYING
sqlparser-0.0.8.dist-info/COPYING.LESSER
sqlparser-0.0.8.dist-info/METADATA
sqlparser-0.0.8.dist-info/WHEEL
sqlparser-0.0.8.dist-info/top_level.txt
sqlparser-0.0.8.dist-info/RECORD
